[
  {
    "id": "11",
    "imgUrl": "/tomat-cat.jpg",
    "title": "Томат Арома F1",
    "pack": "500 насінин",
    "possibility": "Оптом і в роздріб",
    "category": "Томат",
    "parentCategory": "Насіння овочів",
    "price": 325.65
  },
  {
    "id": "21",
    "imgUrl": "/kukurudza-cat.jpg",
    "title": "Кукурудза цукрова Форвард F1 (1709)",
    "pack": "25 000 насінин",
    "possibility": "Оптом і в роздріб",
    "category": "Кукурудза суперсолодка",
    "parentCategory": "Насіння овочів",
    "price": 1245.1
  },
  {
    "id": "31",
    "imgUrl": "/ogirok-cat.jpg",
    "title": "Огірок Бетіна F1",
    "pack": "500 насінин",
    "possibility": "Оптом і в роздріб",
    "category": "Огірок",
    "parentCategory": "Насіння овочів",
    "price": 689.3
  },
  {
    "id": "41",
    "imgUrl": "/soniashnik-cat.jpg",
    "title": "Соняшник P64LP130 (П64ЛП130)",
    "pack": "150 000 насінин",
    "possibility": "Оптом і в роздріб",
    "category": "Соняшник",
    "parentCategory": "Культури",
    "price": 6327.45
  },
  {
    "id": "51",
    "imgUrl": "/tomat-cat.jpg",
    "title": "Кріп Брум F1",
    "pack": "500 насінин",
    "possibility": "Оптом і в роздріб",
    "category": "Родентицид",
    "parentCategory": "Добрива та стимулятори росту",
    "price": 1248.99
  }
]
